pcaper/HTTPRequest.py
pcaper/__init__.py
pcaper/_version.py
pcaper/har2txt.py
pcaper/har_gen.py
pcaper/pcap2txt.py
pcaper/pcap_gen.py
pcaper/pcaper.py
pcaper-1.0.11.dist-info/LICENSE
pcaper-1.0.11.dist-info/METADATA
pcaper-1.0.11.dist-info/WHEEL
pcaper-1.0.11.dist-info/entry_points.txt
pcaper-1.0.11.dist-info/top_level.txt
pcaper-1.0.11.dist-info/RECORD
