Metadata-Version: 2.1
Name: pcaper
Version: 1.0.11
Summary: Read pcap and assemble HTTP requests
Home-page: https://github.com/gaainf/pcaper
Author: Alexander Grechin
Author-email: infinum@mail.ru
License: BSD-3-Clause
Download-URL: https://github.com/gaainf/pcaper
Keywords: traffic pcap utilities tcpdump tshark wireshark
Platform: UNKNOWN
Classifier: Development Status :: 4 - Beta
Classifier: Operating System :: OS Independent
Classifier: Environment :: Console
Classifier: Intended Audience :: Developers
Classifier: License :: OSI Approved :: BSD License
Classifier: Programming Language :: Python :: 2.7
Classifier: Programming Language :: Python :: 3.5
Classifier: Programming Language :: Python :: 3.6
Classifier: Programming Language :: Python :: 3.7
Classifier: Topic :: Software Development
Classifier: Topic :: Utilities
Requires-Dist: dpkt (>=1.9.1)
Requires-Dist: flake8 (>=3.5.0)
Requires-Dist: six (>=1.11.0)
Requires-Dist: python-dateutil (>=2.8.0)
Requires-Dist: zipp (<=1.2.0) ; python_version < "3"
